QianruQianchuFlaskKuangjia/README.md
QianruQianchuFlaskKuangjia/__init__.py
QianruQianchuFlaskKuangjia/__main__.py
QianruQianchuFlaskKuangjia/file.epub
QianruQianchuFlaskKuangjia/index.html
QianruQianchuFlaskKuangjia/css/__init__.py
QianruQianchuFlaskKuangjia/css/annotations.css
QianruQianchuFlaskKuangjia/css/main.css
QianruQianchuFlaskKuangjia/css/normalize.css
QianruQianchuFlaskKuangjia/css/popup.css
QianruQianchuFlaskKuangjia/font/__init__.py
QianruQianchuFlaskKuangjia/font/fontello.eot
QianruQianchuFlaskKuangjia/font/fontello.svg
QianruQianchuFlaskKuangjia/font/fontello.ttf
QianruQianchuFlaskKuangjia/font/fontello.woff
QianruQianchuFlaskKuangjia/img/__init__.py
QianruQianchuFlaskKuangjia/img/annotator-glyph-sprite.png
QianruQianchuFlaskKuangjia/img/annotator-icon-sprite.png
QianruQianchuFlaskKuangjia/img/apple-touch-icon.png
QianruQianchuFlaskKuangjia/img/cancelfullscreen.png
QianruQianchuFlaskKuangjia/img/close.png
QianruQianchuFlaskKuangjia/img/fullscreen.png
QianruQianchuFlaskKuangjia/img/loader.gif
QianruQianchuFlaskKuangjia/img/menu-icon.png
QianruQianchuFlaskKuangjia/img/save.png
QianruQianchuFlaskKuangjia/img/saved.png
QianruQianchuFlaskKuangjia/img/settings-s.png
QianruQianchuFlaskKuangjia/img/settings.png
QianruQianchuFlaskKuangjia/img/star.png
QianruQianchuFlaskKuangjia/js/__init__.py
QianruQianchuFlaskKuangjia/js/epub.js
QianruQianchuFlaskKuangjia/js/epub.min.js
QianruQianchuFlaskKuangjia/js/epub.min.map
QianruQianchuFlaskKuangjia/js/hooks.min.js
QianruQianchuFlaskKuangjia/js/hooks.min.map
QianruQianchuFlaskKuangjia/js/reader.js
QianruQianchuFlaskKuangjia/js/reader.js.map
QianruQianchuFlaskKuangjia/js/reader.min.js
QianruQianchuFlaskKuangjia/js/reader.min.map
QianruQianchuFlaskKuangjia/js/hooks/__init__.py
QianruQianchuFlaskKuangjia/js/hooks/extensions/__init__.py
QianruQianchuFlaskKuangjia/js/hooks/extensions/highlight.js
QianruQianchuFlaskKuangjia/js/libs/__init__.py
QianruQianchuFlaskKuangjia/js/libs/jquery.min.js
qianru_qianchu_flask_kuangjia-2024.3.2.0.dist-info/METADATA
qianru_qianchu_flask_kuangjia-2024.3.2.0.dist-info/WHEEL
qianru_qianchu_flask_kuangjia-2024.3.2.0.dist-info/entry_points.txt
qianru_qianchu_flask_kuangjia-2024.3.2.0.dist-info/top_level.txt
qianru_qianchu_flask_kuangjia-2024.3.2.0.dist-info/RECORD
